nose_progressive-1.5.1.dist-info/DESCRIPTION.rst
nose_progressive-1.5.1.dist-info/entry_points.txt
nose_progressive-1.5.1.dist-info/METADATA
nose_progressive-1.5.1.dist-info/metadata.json
nose_progressive-1.5.1.dist-info/RECORD
nose_progressive-1.5.1.dist-info/top_level.txt
nose_progressive-1.5.1.dist-info/WHEEL
noseprogressive/__init__.py
noseprogressive/bar.py
noseprogressive/plugin.py
noseprogressive/result.py
noseprogressive/runner.py
noseprogressive/tracebacks.py
noseprogressive/utils.py
noseprogressive/wrapping.py
noseprogressive/tests/__init__.py
noseprogressive/tests/test_bar.py
noseprogressive/tests/test_integration.py
noseprogressive/tests/test_tracebacks.py
noseprogressive/tests/test_utils.py
