Metadata-Version: 2.0
Name: nose-progressive
Version: 1.5.1
Summary: A testrunner with a progress bar and smarter tracebacks
Home-page: https://github.com/erikrose/nose-progressive
Author: Erik Rose
Author-email: erikrose@grinchcentral.com
License: MIT
Platform: UNKNOWN
Classifier: Development Status :: 5 - Production/Stable
Classifier: Environment :: Console
Classifier: Intended Audience :: Developers
Classifier: Natural Language :: English
Classifier: License :: OSI Approved :: MIT License
Classifier: Operating System :: OS Independent
Classifier: Programming Language :: Python :: 2
Classifier: Programming Language :: Python :: 2.6
Classifier: Programming Language :: Python :: 2.7
Classifier: Programming Language :: Python :: 3
Classifier: Programming Language :: Python :: 3.2
Classifier: Programming Language :: Python :: 3.3
Classifier: Topic :: Software Development :: Testing
Requires-Dist: nose (>=1.2.1)
Requires-Dist: blessings (>=1.3,<2.0)
